plogpro/__init__.py
plogpro/logger.py
plogpro/logger_impl.py
plogpro/profiler.py
plogpro/profiler_impl.py
plogpro/progressbar.py
plogpro/progressbar_impl.py
plogpro/settings.py
plogpro-1.0.0.dist-info/LICENSE
plogpro-1.0.0.dist-info/METADATA
plogpro-1.0.0.dist-info/WHEEL
plogpro-1.0.0.dist-info/top_level.txt
plogpro-1.0.0.dist-info/RECORD
