Metadata-Version: 2.1
Name: plogpro
Version: 1.0.0
Summary: A simple and versatile Python package for logging, profiling and more
Home-page: https://github.com/wohe157/plogpro
Author: Wouter Heyvaert
Author-email: wouter.heyvaert@hotmail.com
License: GNU General Public License v3 (GPLv3)
Project-URL: Bug Tracker, https://github.com/wohe157/plogpro/issues
Platform: UNKNOWN
Classifier: Programming Language :: Python :: 3
Classifier: License :: OSI Approved :: GNU General Public License v3 (GPLv3)
Classifier: Operating System :: OS Independent
Requires-Python: >=3.6
License-File: LICENSE
